slug_helpers
