Metadata-Version: 1.0
Name: django-slug-helpers
Version: 0.0.3
Summary: A simple model for redirecting from old slugs
Home-page: UNKNOWN
Author: Mark Longair
Author-email: mark-pypi@longair.net
License: AGPL
Keywords: django slugs
Platform: UNKNOWN
